charm/__init__.py
charm/py.typed
charm/adapters/__init__.py
charm/adapters/base.py
charm/adapters/crewai.py
charm/adapters/custom.py
charm/adapters/langchain.py
charm/adapters/langgraph.py
charm/cli/__init__.py
charm/cli/app.py
charm/cli/config.py
charm/cli/git.py
charm/cli/commands/auth.py
charm/cli/commands/config.py
charm/cli/commands/init.py
charm/cli/commands/push.py
charm/cli/commands/run.py
charm/cli/commands/validate.py
charm/contracts/__init__.py
charm/contracts/uac.py
charm/contracts/uac.v0.4.1.schema.json
charm/core/__init__.py
charm/core/callbacks.py
charm/core/errors.py
charm/core/io.py
charm/core/loader.py
charm/core/logger.py
charm/core/memory.py
charm/core/utils.py
charm/core/wrapper.py
charm/runner/__init__.py
charm/runner/executor.py
charm/runner/protocol.py
charm/runner/utils.py
charm/templates/charm.default.yaml
charmos-0.4.20.dist-info/licenses/LICENSE
charmos-0.4.20.dist-info/METADATA
charmos-0.4.20.dist-info/WHEEL
charmos-0.4.20.dist-info/entry_points.txt
charmos-0.4.20.dist-info/top_level.txt
charmos-0.4.20.dist-info/RECORD
