Metadata-Version: 2.4
Name: charmos
Version: 0.4.20
Summary: The Unified System Layer for Agentic Intelligence
Author-email: ucmind <team@charmos.io>
Project-URL: Homepage, https://charmos.io
Project-URL: Repository, https://github.com/CharmAIOS/Charm
Requires-Python: >=3.10
License-File: LICENSE
Requires-Dist: typer>=0.9.0
Requires-Dist: rich>=13.0.0
Requires-Dist: httpx>=0.25.0
Requires-Dist: tomlkit>=0.12.0
Requires-Dist: pydantic>=2.0.0
Requires-Dist: pyyaml>=6.0
Requires-Dist: supabase>=2.0.0
Requires-Dist: gitpython>=3.1.0
Requires-Dist: python-dotenv>=1.0.0
Requires-Dist: langchain>=0.1.0
Requires-Dist: langchain-core
Requires-Dist: langgraph
Requires-Dist: crewai
Provides-Extra: runner
Requires-Dist: docker>=7.0.0; extra == "runner"
Provides-Extra: dev
Requires-Dist: ruff; extra == "dev"
Requires-Dist: pytest; extra == "dev"
Requires-Dist: mypy; extra == "dev"
Requires-Dist: pre-commit; extra == "dev"
Dynamic: license-file
